g4edgetestdata/__init__.py
g4edgetestdata/_version.py
g4edgetestdata/core.py
g4edge_testdata-0.1.0.dist-info/LICENSE
g4edge_testdata-0.1.0.dist-info/METADATA
g4edge_testdata-0.1.0.dist-info/WHEEL
g4edge_testdata-0.1.0.dist-info/top_level.txt
g4edge_testdata-0.1.0.dist-info/RECORD
